touchpoint_client/__about__.py
touchpoint_client/__init__.py
touchpoint_client/_auth.py
touchpoint_client/_client.py
touchpoint_client/_connector.py
touchpoint_client/_decorators.py
touchpoint_client/_profile.py
touchpoint_client/_project.py
touchpoint_client/_storage.py
touchpoint_client/_types_pydantic.py
touchpoint_client/_users.py
touchpoint_client/exceptions.py
touchpoint_client/helpers.py
touchpoint_client/types.py
touchpoint_client-0.3.6.dist-info/METADATA
touchpoint_client-0.3.6.dist-info/WHEEL
touchpoint_client-0.3.6.dist-info/licenses/LICENSE.txt
touchpoint_client-0.3.6.dist-info/RECORD
