Metadata-Version: 2.4
Name: touchpoint-client
Version: 0.3.6
Project-URL: Documentation, http://gitlab.lan/ingest/packages/touchpoint-client#readme
Project-URL: Issues, http://gitlab.lan/ingest/packages/touchpoint-client/issues
Project-URL: Source, http://gitlab.lan/ingest/packages/touchpoint-client
Author-email: Евгений Садовник <e.sadovnik@3itech.ru>
License-Expression: MIT
License-File: LICENSE.txt
Classifier: Development Status :: 4 - Beta
Classifier: Programming Language :: Python
Classifier: Programming Language :: Python :: 3.9
Classifier: Programming Language :: Python :: 3.10
Classifier: Programming Language :: Python :: 3.11
Classifier: Programming Language :: Python :: 3.12
Classifier: Programming Language :: Python :: Implementation :: CPython
Classifier: Programming Language :: Python :: Implementation :: PyPy
Requires-Python: >=3.9
Requires-Dist: httpx
